{"name":"Create a new Stores \u0026 verify if the Stores is added","id":"end-to-end-testing-of-stores-data:Create a new Stores \u0026 verify if the Stores is added","testSteps":[{"number":1,"description":"When I sends the Post Request for create the Stores Data","duration":10,"startTime":"2022-06-19T13:36:01.774+01:00[Europe/London]","result":"SUCCESS","precondition":false},{"number":2,"description":"And I insert the name \"VB \u0026 son\u0027s\",type \"Cash \u0026 carry\",address \"Tooting\",addresss \"london\",city \"London\",state \"South East\",zip \"1234656\",lat \u003d 123456,lng \u003d 123,hours \u003d \"24Hours\"","duration":41,"startTime":"2022-06-19T13:36:01.784+01:00[Europe/London]","result":"SUCCESS","precondition":false,"children":[{"number":3,"description":"This is Create Store with name : VB \u0026 son\u0027s,type: Cash \u0026 carry, address: Tooting, address2: london and city: London,state: South East, zip: \" +\n            \"1234656, lat: 123456 and lng: 123,hours : 24Hours","duration":41,"startTime":"2022-06-19T13:36:01.784+01:00[Europe/London]","result":"SUCCESS","precondition":false,"children":[{"number":4,"description":"POST http://localhost:3030/stores\r\r","duration":0,"startTime":"2022-06-19T13:36:01.825+01:00[Europe/London]","result":"SUCCESS","restQuery":{"method":"POST","path":"http://localhost:3030/stores\r\r","content":"{\n    \"name\": \"VB \u0026 son\u0027s\",\n    \"type\": \"Cash \u0026 carry\",\n    \"address\": \"Tooting\",\n    \"address2\": \"london\",\n    \"city\": \"London\",\n    \"state\": \"South East\",\n    \"zip\": \"1234656\",\n    \"lat\": 123456,\n    \"lng\": 123,\n    \"hours\": \"24Hours\"\n}\r","contentType":"application/json","requestHeaders":"Accept\u003d*/*\r\n\t\t\t\tContent-Type\u003dapplication/json; charset\u003dUTF-8\r\r","requestCookies":"\r\r","responseHeaders":"X-Powered-By: Express\nAccess-Control-Allow-Origin: *\nAllow: GET,POST,PUT,PATCH,DELETE\nVary: Accept, Accept-Encoding\nContent-Type: application/json; charset\u003dutf-8\nContent-Length: 265\nETag: W/\"109-WK8jskmpV1RQ297DypfdC0wuiTY\"\nDate: Sun, 19 Jun 2022 12:36:01 GMT\nConnection: keep-alive\r","responseCookies":"\r","responseBody":"{\n    \"id\": 8936,\n    \"name\": \"VB \u0026 son\u0027s\",\n    \"type\": \"Cash \u0026 carry\",\n    \"address\": \"Tooting\",\n    \"address2\": \"london\",\n    \"city\": \"London\",\n    \"state\": \"South East\",\n    \"zip\": \"1234656\",\n    \"lat\": 123456,\n    \"lng\": 123,\n    \"hours\": \"24Hours\",\n    \"updatedAt\": \"2022-06-19T12:36:01.816Z\",\n    \"createdAt\": \"2022-06-19T12:36:01.816Z\"\n}","statusCode":201},"precondition":false}]}]},{"number":5,"description":"Then I verify the status code 201 for Stores data","duration":0,"startTime":"2022-06-19T13:36:01.825+01:00[Europe/London]","result":"SUCCESS","precondition":false},{"number":6,"description":"And I get the id of new created Stores data","duration":12,"startTime":"2022-06-19T13:36:01.825+01:00[Europe/London]","result":"SUCCESS","precondition":false}],"userStory":{"id":"end-to-end-testing-of-stores-data","storyName":"End to End testing of Stores data","path":"Store.feature","type":"feature"},"featureTag":{"name":"End to End testing of Stores data","type":"feature"},"title":"Create a new Stores \u0026 verify if the Stores is added","description":"","tags":[{"name":"End to End testing of Stores data","type":"feature"}],"startTime":"2022-06-19T13:36:01.774+01:00[Europe/London]","duration":63,"projectKey":"","manual":false,"result":"SUCCESS"}